LICENSE
MANIFEST.in
setup.py
pyswagg/__init__.py
pyswagg/core.py
pyswagg/errs.py
pyswagg/getter.py
pyswagg/io.py
pyswagg/resolve.py
pyswagg/scan.py
pyswagg/utils.py
pyswagg.egg-info/PKG-INFO
pyswagg.egg-info/SOURCES.txt
pyswagg.egg-info/dependency_links.txt
pyswagg.egg-info/requires.txt
pyswagg.egg-info/top_level.txt
pyswagg/consts/__init__.py
pyswagg/consts/private.py
pyswagg/contrib/__init__.py
pyswagg/contrib/client/__init__.py
pyswagg/contrib/client/flask.py
pyswagg/contrib/client/requests.py
pyswagg/contrib/client/tornado.py
pyswagg/contrib/client/webapp2.py
pyswagg/primitives/__init__.py
pyswagg/primitives/_array.py
pyswagg/primitives/_bool.py
pyswagg/primitives/_byte.py
pyswagg/primitives/_file.py
pyswagg/primitives/_float.py
pyswagg/primitives/_int.py
pyswagg/primitives/_model.py
pyswagg/primitives/_str.py
pyswagg/primitives/_time.py
pyswagg/primitives/_uuid.py
pyswagg/primitives/codec.py
pyswagg/primitives/comm.py
pyswagg/primitives/render.py
pyswagg/scanner/__init__.py
pyswagg/scanner/cycle_detector.py
pyswagg/scanner/type_reducer.py
pyswagg/scanner/v1_2/__init__.py
pyswagg/scanner/v1_2/upgrade.py
pyswagg/scanner/v1_2/validate.py
pyswagg/scanner/v2_0/__init__.py
pyswagg/scanner/v2_0/aggt.py
pyswagg/scanner/v2_0/assign_parent.py
pyswagg/scanner/v2_0/merge.py
pyswagg/scanner/v2_0/norm_ref.py
pyswagg/scanner/v2_0/patch_obj.py
pyswagg/scanner/v2_0/resolve.py
pyswagg/scanner/v2_0/validate.py
pyswagg/scanner/v2_0/yaml.py
pyswagg/spec/__init__.py
pyswagg/spec/base.py
pyswagg/spec/v1_2/__init__.py
pyswagg/spec/v1_2/objects.py
pyswagg/spec/v1_2/parser.py
pyswagg/spec/v2_0/__init__.py
pyswagg/spec/v2_0/objects.py
pyswagg/spec/v2_0/parser.py