Metadata-Version: 2.1
Name: pyswagg
Version: 0.8.41
Summary: A type-safe, dynamic, spec-compliant swagger client & converter for python
Home-page: https://github.com/benkilimnik/pyswagg
Author: Mission Liao / benkilimnik
Author-email: missionaryliao@gmail.com
License: UNKNOWN
Download-URL: https://github.com/benkilimnik/pyswagg/tarball/0.8.41
Keywords: swagger,REST
Platform: UNKNOWN
Classifier: Development Status :: 4 - Beta
Classifier: Intended Audience :: Developers
Classifier: License :: OSI Approved :: MIT License
Classifier: Operating System :: OS Independent
Classifier: Programming Language :: Python :: 2.6
Classifier: Programming Language :: Python :: 2.7
Classifier: Programming Language :: Python :: 3.3
Classifier: Programming Language :: Python :: 3.4
Classifier: Topic :: Software Development :: Libraries :: Python Modules
License-File: LICENSE
